16x8_Dual_Port_RAM_With_Two_Clocks/design.sv
// Code your design here

// I'm designing 16x8 dual port ram where data width = 8, depth or number of memory location = 16, and address width =  4 ( as 2^4 = 16 )
module dual_port_ram #(
  parameter data_width = 8,
  parameter addr_width = 4,
  parameter depth = 16
)(
  input clk0, clk1,
  input rst,

  input [data_width-1:0] din_a,
  input [addr_width-1:0] addr_a,
  input we_a, re_a,
  output reg [data_width-1:0] dout_a,

  input [data_width-1:0] din_b,
  input [addr_width-1:0] addr_b,
  input we_b, re_b,
  output reg [data_width-1:0] dout_b
);

  reg [data_width-1:0] mem[0:depth-1];
  integer i;

  // Reset logic
  always @(posedge rst) begin
    for (i = 0; i < depth; i = i + 1)
      mem[i] <= 0;

    dout_a <= 0;
    dout_b <= 0;
  end

  // Port A
  always @(posedge clk0) begin
    if (!rst) begin
      if (we_a)
        mem[addr_a] <= din_a;
      if (re_a)
        dout_a <= mem[addr_a];
    end
  end

  // Port B
  always @(posedge clk1) begin
    if (!rst) begin
      if (we_b)
        mem[addr_b] <= din_b;
      if (re_b)
        dout_b <= mem[addr_a]; // read input data of port-A from Port-B 
    end
  end

endmodule

16x8_Dual_Port_RAM_With_Two_Clocks/testbench.sv
`timescale 1ns/1ps
module tb;

  reg clk0 = 0, clk1 = 0;
  reg [7:0] din_a, din_b;
  reg [3:0] addr_a, addr_b;
  reg we_a, we_b;
  reg re_a, re_b;
  wire [7:0] dout_a, dout_b;
  reg rst;

  dual_port_ram dut(
    .clk0(clk0), 
    .clk1(clk1),
    .rst(rst),
    .din_a(din_a), .din_b(din_b),
    .dout_a(dout_a), .dout_b(dout_b),
    .addr_a(addr_a), .addr_b(addr_b),
    .we_a(we_a), .we_b(we_b),
    .re_a(re_a), .re_b(re_b)
  );

  always #5 clk0 = ~clk0;  // 100 MHz
  always #10 clk1 = ~clk1; // 50 MHz

  initial begin

    $dumpfile("test_ram.vcd");
    $dumpvars(0, tb);
    
    
    $monitor("Time = %t | Din_a = %b | Din_b = %b | addr_a = %b | addr_b = %b | we_a = %b | we_b = %b | @addr_a = %b | @addr_b = %b | re_a = %b | re_b = %b | rst = %b | dout_a = %b | dout_b = %b", $realtime, din_a, din_b, addr_a, addr_b, we_a, we_b, dut.mem[addr_a], dut.mem[addr_b], re_a, re_b, rst, dout_a, dout_b);

    din_a = 8'b1; din_b = 8'b10;
    addr_a = 4'b1010; addr_b = 4'b1111;
    we_a = 0; we_b = 0;
    re_a = 0; re_b = 0;
    rst = 1;

    #1 rst = 0; 

    // Write from Port A and Read from Port-B
    
    // As frequency of writing of port-A is more and frequency of reading of port-B is low, port-B will miss to read some data written by Port-A. 
    
    // Port-A is fast, Port-B is slow.
    
    @(posedge clk0); we_a = 1;
    @(posedge clk1); re_b = 1;
    @(posedge clk0); din_a = 8'b11;
    @(posedge clk0); din_a = 8'b111;
    @(posedge clk0); din_a = 8'b11010;
    @(posedge clk0); din_a = 8'b10101;
    @(posedge clk0); din_a = 8'b01010;
    @(posedge clk0); din_a = 8'b1111111;
    @(posedge clk0); din_a = 8'b00110011;
    @(posedge clk0); din_a = 8'b11100011;
    @(posedge clk0); din_a = 8'b1101001;
    @(posedge clk0); we_a = 0;
    @(posedge clk1); re_b = 0;

    #10 $finish;
  end

endmodule

16x8_Dual_Port_RAM_With_Two_Clocks/test_ram.vcd
$date
	Sat Jun  7 02:23:50 2025
$end

$version
	Synopsys VCS version U-2023.03-SP2_Full64
$end

$timescale
	1ps
$end

$comment Csum: 1 40f8e4e7d274061d $end


$scope module tb $end
$var reg 1 ! clk0 $end
$var reg 1 " clk1 $end
$var reg 8 # din_a [7:0] $end
$var reg 8 $ din_b [7:0] $end
$var reg 4 % addr_a [3:0] $end
$var reg 4 & addr_b [3:0] $end
$var reg 1 ' we_a $end
$var reg 1 ( we_b $end
$var reg 1 ) re_a $end
$var reg 1 * re_b $end
$var wire 8 + dout_a [7:0] $end
$var wire 8 , dout_b [7:0] $end
$var reg 1 - rst $end

$scope module dut $end
$var wire 1 ! clk0 $end
$var wire 1 " clk1 $end
$var wire 1 - rst $end
$var wire 8 # din_a [7:0] $end
$var wire 4 % addr_a [3:0] $end
$var wire 1 ' we_a $end
$var wire 1 ) re_a $end
$var reg 8 + dout_a [7:0] $end
$var wire 8 $ din_b [7:0] $end
$var wire 4 & addr_b [3:0] $end
$var wire 1 ( we_b $end
$var wire 1 * re_b $end
$var reg 8 , dout_b [7:0] $end
$var integer 32 . i $end
$upscope $end

$upscope $end

$enddefinitions $end

#0
$dumpvars
0!
0"
0)
0*
1-
0'
0(
b1010 %
b1111 &
b00000001 #
b00000010 $
b00000000 +
b00000000 ,
b00000000000000000000000000010000 .
$end
#1000
0-
#5000
1!
1'
#10000
1"
0!
1*
b00000001 ,
#15000
1!
b00000011 #
#20000
0"
0!
#25000
1!
b00000111 #
#30000
1"
0!
b00000111 ,
#35000
1!
b00011010 #
#40000
0"
0!
#45000
1!
b00010101 #
#50000
1"
0!
b00010101 ,
#55000
1!
b00001010 #
#60000
0"
0!
#65000
1!
b01111111 #
#70000
1"
0!
b01111111 ,
#75000
1!
b00110011 #
#80000
0"
0!
#85000
1!
b11100011 #
#90000
1"
0!
b11100011 ,
#95000
1!
b01101001 #
#100000
0"
0!
#105000
1!
0'
#110000
1"
0!
0*
